silver_braintree/__init__.py
silver_braintree/_version.py
silver_braintree/payment_processors.py
silver_braintree/views.py
silver_braintree/api/__init__.py
silver_braintree/api/views.py
silver_braintree/migrations/0001_initial.py
silver_braintree/migrations/__init__.py
silver_braintree/models/__init__.py
silver_braintree/models/customer_data.py
silver_braintree/models/payment_methods.py
silver_braintree/templates/forms/braintree/braintree_ui.html
silver_braintree/templates/forms/braintree/transaction_form.html
silver_braintree-0.1.0.dist-info/DESCRIPTION.rst
silver_braintree-0.1.0.dist-info/METADATA
silver_braintree-0.1.0.dist-info/RECORD
silver_braintree-0.1.0.dist-info/WHEEL
silver_braintree-0.1.0.dist-info/metadata.json
silver_braintree-0.1.0.dist-info/top_level.txt
tests/__init__.py
tests/conftest.py
tests/factories.py
tests/test_payment_processors.py
