Metadata-Version: 2.0
Name: silver-braintree
Version: 0.1.0
Summary: UNKNOWN
Home-page: https://github.com/silverapp/silver-braintree
Author: Presslabs
Author-email: ping@presslabs.com
License: Apache 2.0
Keywords: django,app,reusable,billing,invoicing,api
Platform: OS Independent
Classifier: Environment :: Web Environment
Classifier: Framework :: Django :: 1.8
Classifier: Development Status :: 5 - Production/Stable
Classifier: License :: OSI Approved :: Apache Software License
Classifier: Programming Language :: Python :: 2.7
Requires-Dist: braintree
